django_zarinpal/__init__.py
django_zarinpal/admin.py
django_zarinpal/apps.py
django_zarinpal/config.py
django_zarinpal/exceptions.py
django_zarinpal/migrations/0001_initial.py
django_zarinpal/migrations/__init__.py
django_zarinpal/models.py
django_zarinpal/services.py
django_zarinpal/signals.py
django_zarinpal/urls.py
django_zarinpal/views.py
django_zarinpal-1.0.0.dist-info/LICENSE
django_zarinpal-1.0.0.dist-info/WHEEL
django_zarinpal-1.0.0.dist-info/METADATA
django_zarinpal-1.0.0.dist-info/RECORD
