Metadata-Version: 2.1
Name: django-zarinpal
Version: 1.0.0
Summary: integrate django payments with zarrinpal
License: MIT
Author: glyphack
Author-email: sh.hooshyari@gmail.com
Requires-Python: >=3.5,<4.0
Classifier: License :: OSI Approved :: MIT License
Classifier: Programming Language :: Python :: 3
Classifier: Programming Language :: Python :: 3.5
Classifier: Programming Language :: Python :: 3.6
Classifier: Programming Language :: Python :: 3.7
Classifier: Programming Language :: Python :: 3.8
Requires-Dist: django-hashid-field (>=3.1.1,<4.0.0)
Requires-Dist: zeep (>=3.4.0,<4.0.0)
